jsonschema_gen/__init__.py
jsonschema_gen/parsers.py
jsonschema_gen/schema.py
jsonschema_gen/utils.py
jsonschema_gen-0.1.1.dist-info/LICENSE
jsonschema_gen-0.1.1.dist-info/METADATA
jsonschema_gen-0.1.1.dist-info/WHEEL
jsonschema_gen-0.1.1.dist-info/top_level.txt
jsonschema_gen-0.1.1.dist-info/RECORD
